pydvh/__init__.py
pydvh/dvhdata.py
pydvh/dvhfile.py
pydvh-1.0.9.dist-info/LICENSE.txt
pydvh-1.0.9.dist-info/METADATA
pydvh-1.0.9.dist-info/WHEEL
pydvh-1.0.9.dist-info/top_level.txt
pydvh-1.0.9.dist-info/RECORD
